hubspot_integration_server_core/__init__.py
hubspot_integration_server_core/celery_app.py
hubspot_integration_server_core/config.py
hubspot_integration_server_core/hubspot_integration_server.py
hubspot_integration_server_core/utils.py
hubspot_integration_server_core/database/__init__.py
hubspot_integration_server_core/database/database.py
hubspot_integration_server_core/database/init_db.py
hubspot_integration_server_core/models/__init__.py
hubspot_integration_server_core/models/hubspotcredentials.py
hubspot_integration_server_core/oauth_server/__init__.py
hubspot_integration_server_core/oauth_server/handlers.py
hubspot_integration_server_core/oauth_server/helpers.py
hubspot_integration_server_core/routes/__init__.py
hubspot_integration_server_core/services/__init__.py
hubspot_integration_server_core/services/hubspot/__init__.py
hubspot_integration_server_core/services/hubspot/hubspot_app_service.py
hubspot_integration_server_core/services/hubspot/hubspot_portal_service.py
hubspot_integration_server-0.1.1.dist-info/LICENSE
hubspot_integration_server-0.1.1.dist-info/METADATA
hubspot_integration_server-0.1.1.dist-info/WHEEL
hubspot_integration_server-0.1.1.dist-info/top_level.txt
hubspot_integration_server-0.1.1.dist-info/RECORD
