Metadata-Version: 2.1
Name: hubspot_integration_server
Version: 0.1.1
Summary: A server for integrating with HubSpot using Flask and Celery
Home-page: https://example.com/project-url
Author: Your Name
Author-email: Your Name <your.email@example.com>
License: MIT
Project-URL: Homepage, https://example.com/project-url
Classifier: Development Status :: 3 - Alpha
Classifier: Intended Audience :: Developers
Classifier: License :: OSI Approved :: MIT License
Classifier: Programming Language :: Python :: 3
Classifier: Programming Language :: Python :: 3.8
Classifier: Framework :: Flask
Requires-Python: >=3.6
License-File: LICENSE
Requires-Dist: flask
Requires-Dist: flask-sqlalchemy
Requires-Dist: python-dotenv
Requires-Dist: hubspot-api-client-extended
Requires-Dist: redis
Requires-Dist: celery
Requires-Dist: alembic
